etalumacontrol/__init__.py
etalumacontrol/definitions.py
etalumacontrol/lumascope.py
etalumacontrol/stage.py
etalumacontrol/CypressFX/__init__.py
etalumacontrol/resources/Lumascope600.hex
etalumacontrol/resources/lib/x64/LumaUSB.dll
etalumacontrol/resources/lib/x64/wsc64.dll
etalumacontrol/resources/lib/x86/LumaUSB.dll
etalumacontrol/resources/lib/x86/wsc32.dll
etalumacontrol-0.1.1.dist-info/LICENSE
etalumacontrol-0.1.1.dist-info/METADATA
etalumacontrol-0.1.1.dist-info/WHEEL
etalumacontrol-0.1.1.dist-info/top_level.txt
etalumacontrol-0.1.1.dist-info/RECORD
