Metadata-Version: 2.1
Name: etalumacontrol
Version: 0.1.1
Summary: Library for interacting with Etaluma microscopes and stages
Home-page: https://github.com/jonasoh/etalumacontrol
Author: Jonas Ohlsson
Author-email: jonas.ohlsson@slu.se
License: BSD license
Platform: UNKNOWN
Classifier: Development Status :: 3 - Alpha
Classifier: Operating System :: Microsoft :: Windows
Classifier: Topic :: Scientific/Engineering
License-File: LICENSE
Requires-Dist: intelhex (>=2.3.0)
Requires-Dist: Pillow (>=8.3.1)
Requires-Dist: pycparser (>=2.20)
Requires-Dist: pythonnet (>=2.5.2)
Requires-Dist: pyusb (>=1.2.1)
